{
    "name": "ProductCommerce",
    "fields": [
        {
            "fieldName": "price",
            "fieldType": "Float"
        },
        {
            "fieldName": "quantity",
            "fieldType": "Integer"
        }
    ],
    "relationships": [
        {
            "relationshipName": "product",
            "otherEntityName": "product",
            "relationshipType": "many-to-one",
            "otherEntityField": "id"
        },
        {
            "relationshipType": "one-to-many",
            "otherEntityName": "commerce",
            "otherEntityRelationshipName": "productCommerce",
            "relationshipName": "commerce"
        },
        {
            "relationshipType": "many-to-many",
            "otherEntityName": "productList",
            "otherEntityRelationshipName": "productCommerce",
            "relationshipName": "productList",
            "otherEntityField": "id",
            "ownerSide": true
        }
    ],
    "changelogDate": "20190312191710",
    "entityTableName": "product_commerce",
    "dto": "no",
    "pagination": "no",
    "service": "no",
    "jpaMetamodelFiltering": false,
    "fluentMethods": true,
    "clientRootFolder": "",
    "applications": "*"
}